LICENSE
MANIFEST.in
README.md
setup.cfg
setup.py
refreshable.egg-info/PKG-INFO
refreshable.egg-info/SOURCES.txt
refreshable.egg-info/dependency_links.txt
refreshable.egg-info/pbr.json
refreshable.egg-info/top_level.txt
refreshable.egg-info/zip-safe
src/__init__.py
src/refreshable.py