Metadata-Version: 1.1
Name: refreshable
Version: 1.0.1
Summary: Tools for livecoding performances
Home-page: https://github.com/zbanks/doitlive
Author: Zach Banks
Author-email: zbanks@mit.edu
License: UNKNOWN
Download-URL: https://github.com/zbanks/doitlive/tarball/1.0.1
Platform: UNKNOWN
